examples/__init__.py
examples/example_arago_poisson.py
examples/example_ideal_lens.py
examples/json_tools.py
examples/propagation_scaling_therorem_1D.py
examples/propagation_spherical_wave.py
examples/run_wofry_beamline_and_dump_files.py
examples/run_wofry_beamline_from_files.py
test/__init__.py
test/propagators1D_test.py
test/propagators2D_test.py
test/wavefronts_test.py
test/propagators/__init__.py
test/propagators/srw_fresnel.py
wofryimpl/__init__.py
wofryimpl/version.py
wofryimpl/beamline/__init__.py
wofryimpl/beamline/beamline.py
wofryimpl/beamline/optical_elements/__init__.py
wofryimpl/beamline/optical_elements/absorbers/__init__.py
wofryimpl/beamline/optical_elements/absorbers/beam_stopper.py
wofryimpl/beamline/optical_elements/absorbers/slit.py
wofryimpl/beamline/optical_elements/ideal_elements/__init__.py
wofryimpl/beamline/optical_elements/ideal_elements/ideal_lens.py
wofryimpl/beamline/optical_elements/ideal_elements/screen.py
wofryimpl/beamline/optical_elements/mirrors/__init__.py
wofryimpl/beamline/optical_elements/mirrors/mirror.py
wofryimpl/beamline/optical_elements/refractors/__init__.py
wofryimpl/beamline/optical_elements/refractors/lens.py
wofryimpl/beamline/optical_elements/refractors/thin_object.py
wofryimpl/beamline/optical_elements/refractors/thin_object_corrector.py
wofryimpl/beamline/optical_elements/util/__init__.py
wofryimpl/beamline/optical_elements/util/arrayofvectors.py
wofryimpl/beamline/optical_elements/util/s4_conic.py
wofryimpl/beamline/optical_elements/util/s4_optical_surface.py
wofryimpl/propagator/__init__.py
wofryimpl/propagator/light_source.py
wofryimpl/propagator/light_source_cmd.py
wofryimpl/propagator/light_source_h5file.py
wofryimpl/propagator/light_source_pysru.py
wofryimpl/propagator/propagators1D/__init__.py
wofryimpl/propagator/propagators1D/fraunhofer.py
wofryimpl/propagator/propagators1D/fresnel.py
wofryimpl/propagator/propagators1D/fresnel_convolution.py
wofryimpl/propagator/propagators1D/fresnel_zoom.py
wofryimpl-1.0.34.dist-info/licenses/LICENSE
wofryimpl-1.0.34.dist-info/METADATA
wofryimpl-1.0.34.dist-info/WHEEL
wofryimpl-1.0.34.dist-info/top_level.txt
wofryimpl-1.0.34.dist-info/RECORD
